boning/__init__.py
boning/functional.py
boning/optimizer.py
boning/utils.py
boning/variable.py
boning/network/__init__.py
boning/network/linear.py
boning/network/net.py
Boning-0.0.1.dist-info/METADATA
Boning-0.0.1.dist-info/WHEEL
Boning-0.0.1.dist-info/top_level.txt
Boning-0.0.1.dist-info/RECORD
