Metadata-Version: 2.1
Name: Boning
Version: 0.0.1
Summary: 
Home-page: https://gitee.com/zrr1999/
Author: 六个骨头
Author-email: 2742392377@qq.com
License: UNKNOWN
Platform: any
Classifier: Programming Language :: Python :: 3
Classifier: License :: OSI Approved :: GNU Lesser General Public License v3 (LGPLv3)
Classifier: Operating System :: OS Independent
Requires-Dist: bonelate
Requires-Dist: bonerator
Provides-Extra: command
Requires-Dist: typer ; extra == 'command'
Provides-Extra: parse
Requires-Dist: pyparsing ; extra == 'parse'
Provides-Extra: server
Requires-Dist: fastapi ; extra == 'server'
Requires-Dist: pydantic ; extra == 'server'
Requires-Dist: uvicorn (>=0.3.0) ; extra == 'server'
